<?xml version="1.0"?>
<!DOCTYPE resources SYSTEM "resources.dtd">
<resources version="1.0">  
    <set basename="GlobalResources">
        <resource id="1" type="string" name="LOCALE_ENGLISH">	
            <value>English</value>						
        </resource>
        <resource id="2" type="string" name="LOCALE_SPANISH">	
            <value>Español</value>						
        </resource>
        <resource id="3" type="string" name="LOCALE_GERMAN">	
            <value>Deutsch</value>						
        </resource>
        <resource id="4" type="string" name="LOCALE_FRENCH">	
            <value>Français</value>						
        </resource>
        <resource id="5" type="string" name="LOCALE_ITALIAN">	
            <value>Italiano</value>						
        </resource>
        <resource id="6" type="string" name="GSM_LANG">		
            <value locale="en-GB">en</value>	
            <value locale="es-ES">es</value>	
            <value locale="de-DE">de</value>	
            <value locale="fr-FR">fr</value>	
            <value locale="it-IT">it</value>	
        </resource>
        <resource id="8" type="string" name="TXT_COMMON_BACK">		
            <value locale="en-GB">Back</value>	
            <value locale="es-ES">Volver</value>	
            <value locale="de-DE">Zurück</value>	
            <value locale="fr-FR">Retour</value>	
            <value locale="it-IT">Indietro</value>	
        </resource>
        <resource id="9" type="string" name="TXT_COMMON_EXIT">		
            <value locale="en-GB">Exit</value>	
            <value locale="es-ES">Salir</value>	
            <value locale="de-DE">Verlassen</value>	
            <value locale="fr-FR">Quitter</value>	
            <value locale="it-IT">Uscita</value>	
        </resource>
        <resource id="10" type="string" name="TXT_COMMON_OPTIONS">		
            <value locale="en-GB">Options</value>	
            <value locale="es-ES">Opciones</value>	
            <value locale="de-DE">Optionen</value>	
            <value locale="fr-FR">Options</value>	
            <value locale="it-IT">Opzioni</value>	
        </resource>
        <resource id="11" type="string" name="TXT_COMMON_SELECT">		
            <value locale="en-GB">Select</value>	
            <value locale="es-ES">Seleccionar</value>	
            <value locale="de-DE">Auswählen</value>	
            <value locale="fr-FR">Sélectionner</value>	
            <value locale="it-IT">Seleziona</value>	
        </resource>
        <resource id="12" type="string" name="TXT_COMMON_SAVE">		
            <value locale="en-GB">Save</value>	
            <value locale="es-ES">Guardar</value>	
            <value locale="de-DE">Speichern</value>	
            <value locale="fr-FR">Enregistrer</value>	
            <value locale="it-IT">Salva</value>	
        </resource>
        <resource id="13" type="string" name="TXT_COMMON_YES">		
            <value locale="en-GB">Yes</value>	
            <value locale="es-ES">Sí</value>	
            <value locale="de-DE">Ja</value>	
            <value locale="fr-FR">Oui</value>	
            <value locale="it-IT">Sì</value>	
        </resource>
        <resource id="14" type="string" name="TXT_COMMON_NO">		
            <value locale="en-GB">No</value>	
            <value locale="es-ES">No</value>	
            <value locale="de-DE">Nein</value>	
            <value locale="fr-FR">Non</value>	
            <value locale="it-IT">No</value>	
        </resource>
        <resource id="15" type="string" name="TXT_COMMON_OK">		
            <value locale="en-GB">OK</value>	
            <value locale="es-ES">OK</value>	
            <value locale="de-DE">OK</value>	
            <value locale="fr-FR">OK</value>	
            <value locale="it-IT">OK</value>	
        </resource>
        <resource id="16" type="string" name="TXT_COMMON_CANCEL">		
            <value locale="en-GB">Cancel</value>	
            <value locale="es-ES">Cancelar</value>	
            <value locale="de-DE">Löschen</value>	
            <value locale="fr-FR">Annuler</value>	
            <value locale="it-IT">Annullare</value>	
        </resource>
        <resource id="17" type="string" name="TXT_COMMON_PLEASE_WAIT">		
            <value locale="en-GB">Please Wait</value>	
            <value locale="es-ES">Por favor, espere</value>	
            <value locale="de-DE">Bitte warten</value>	
            <value locale="fr-FR">Veuillez patienter</value>	
            <value locale="it-IT">Attendere Prego</value>	
        </resource>
        <resource id="18" type="string" name="TXT_COMMON_GATHERING_INFO">		
            <value locale="en-GB">Gathering information</value>	
            <value locale="es-ES">Recopilando información</value>	
            <value locale="de-DE">Informationen werden gesammelt</value>	
            <value locale="fr-FR">Regrouper les informations</value>	
            <value locale="it-IT">Ricerca dati in atto</value>	
        </resource>
        <resource id="19" type="string" name="TXT_COMMON_CLOSE">		
            <value locale="en-GB">Close</value>	
            <value locale="es-ES">Cerrar</value>	
            <value locale="de-DE">Schließen</value>	
            <value locale="fr-FR">Fermer</value>	
            <value locale="it-IT">Chiudi</value>	
        </resource>
        <resource id="20" type="string" name="TXT_COMMON_HELP">		
            <value locale="en-GB">Help</value>	
            <value locale="es-ES">Ayuda</value>	
            <value locale="de-DE">Hilfe</value>	
            <value locale="fr-FR">Assitance</value>	
            <value locale="it-IT">Aiuto</value>	
        </resource>
        <resource id="21" type="string" name="TXT_ENTER_PASSWORD">		
            <value locale="en-GB">Please enter your password</value>	
            <value locale="es-ES">Por favor, introduzca su contraseña</value>	
            <value locale="de-DE">Bitte geben Sie Ihr Passwort ein.</value>	
            <value locale="fr-FR">Veuillez entrer votre mot de passe</value>	
            <value locale="it-IT">Inserisci la tua password</value>	
        </resource>
        <resource id="22" type="string" name="TXT_ENTER">		
            <value locale="en-GB">Enter</value>	
            <value locale="es-ES">Entrar</value>	
            <value locale="de-DE">Eingeben</value>	
            <value locale="fr-FR">Entrer</value>	
            <value locale="it-IT">Entrare</value>	
        </resource>
        <resource id="23" type="string" name="TXT_JAN">		
            <value locale="en-GB">January</value>	
            <value locale="es-ES">Enero</value>	
            <value locale="de-DE">Januar</value>	
            <value locale="fr-FR">Janvier</value>	
            <value locale="it-IT">Gennaio</value>	
        </resource>
        <resource id="24" type="string" name="TXT_FEB">		
            <value locale="en-GB">February</value>	
            <value locale="es-ES">Febrero</value>	
            <value locale="de-DE">Februar</value>	
            <value locale="fr-FR">Fevrier</value>	
            <value locale="it-IT">Febbraio</value>	
        </resource>
        <resource id="25" type="string" name="TXT_MAR">		
            <value locale="en-GB">March</value>	
            <value locale="es-ES">Marzo</value>	
            <value locale="de-DE">März</value>	
            <value locale="fr-FR">Mars</value>	
            <value locale="it-IT">Marzo</value>	
        </resource>
        <resource id="26" type="string" name="TXT_APR">		
            <value locale="en-GB">April</value>	
            <value locale="es-ES">Abril</value>	
            <value locale="de-DE">April</value>	
            <value locale="fr-FR">Avril</value>	
            <value locale="it-IT">Aprile</value>	
        </resource>
        <resource id="27" type="string" name="TXT_MAY">		
            <value locale="en-GB">May</value>	
            <value locale="es-ES">Mayo</value>	
            <value locale="de-DE">Mai</value>	
            <value locale="fr-FR">Mai</value>	
            <value locale="it-IT">Maggio</value>	
        </resource>
        <resource id="28" type="string" name="TXT_JUN">		
            <value locale="en-GB">June</value>	
            <value locale="es-ES">​​Junio</value>	
            <value locale="de-DE">Juni</value>	
            <value locale="fr-FR">Juin</value>	
            <value locale="it-IT">Giugno</value>	
        </resource>
        <resource id="29" type="string" name="TXT_JULY">		
            <value locale="en-GB">July</value>	
            <value locale="es-ES">​​Julio</value>	
            <value locale="de-DE">Juli</value>	
            <value locale="fr-FR">Juillet</value>	
            <value locale="it-IT">Luglio</value>	
        </resource>
        <resource id="30" type="string" name="TXT_AUG">		
            <value locale="en-GB">August</value>	
            <value locale="es-ES">Agosto</value>	
            <value locale="de-DE">August</value>	
            <value locale="fr-FR">Août</value>	
            <value locale="it-IT">Agosto</value>	
        </resource>
        <resource id="31" type="string" name="TXT_SEP">		
            <value locale="en-GB">September</value>	
            <value locale="es-ES">Septiembre</value>	
            <value locale="de-DE">September</value>	
            <value locale="fr-FR">Septembre</value>	
            <value locale="it-IT">Settembre</value>	
        </resource>
        <resource id="32" type="string" name="TXT_OCT">		
            <value locale="en-GB">October</value>	
            <value locale="es-ES">Octubre</value>	
            <value locale="de-DE">Oktober</value>	
            <value locale="fr-FR">Octobre</value>	
            <value locale="it-IT">Ottobre</value>	
        </resource>
        <resource id="33" type="string" name="TXT_NOV">		
            <value locale="en-GB">November</value>	
            <value locale="es-ES">De noviembre</value>	
            <value locale="de-DE">November</value>	
            <value locale="fr-FR">Novembre</value>	
            <value locale="it-IT">Novembre</value>	
        </resource>
        <resource id="34" type="string" name="TXT_DEC">		
            <value locale="en-GB">December</value>	
            <value locale="es-ES">Diciembre</value>	
            <value locale="de-DE">Dezember</value>	
            <value locale="fr-FR">Décembre</value>	
            <value locale="it-IT">Dicembre</value>	
        </resource>
        <resource id="35" type="string" name="TXT_MON">		
            <value locale="en-GB">Mon</value>	
            <value locale="es-ES">Lun</value>	
            <value locale="de-DE">Mon</value>	
            <value locale="fr-FR">Lun</value>	
            <value locale="it-IT">Lun</value>	
        </resource>
        <resource id="36" type="string" name="TXT_TUE">		
            <value locale="en-GB">Tue</value>	
            <value locale="es-ES">Mar</value>	
            <value locale="de-DE">Die</value>	
            <value locale="fr-FR">Mar</value>	
            <value locale="it-IT">Mar</value>	
        </resource>
        <resource id="37" type="string" name="TXT_WED">		
            <value locale="en-GB">Wed</value>	
            <value locale="es-ES">Mié</value>	
            <value locale="de-DE">Mit</value>	
            <value locale="fr-FR">Mer</value>	
            <value locale="it-IT">Mer</value>	
        </resource>
        <resource id="38" type="string" name="TXT_THURS">		
            <value locale="en-GB">Thr</value>	
            <value locale="es-ES">Jue</value>	
            <value locale="de-DE">Don</value>	
            <value locale="fr-FR">Jeu</value>	
            <value locale="it-IT">Gio</value>	
        </resource>
        <resource id="39" type="string" name="TXT_FRI">		
            <value locale="en-GB">Fri</value>	
            <value locale="es-ES">Vie</value>	
            <value locale="de-DE">Fre</value>	
            <value locale="fr-FR">Ven</value>	
            <value locale="it-IT">Ven</value>	
        </resource>
        <resource id="40" type="string" name="TXT_SAT">		
            <value locale="en-GB">Sat</value>	
            <value locale="es-ES">Sáb</value>	
            <value locale="de-DE">Sam</value>	
            <value locale="fr-FR">Sam</value>	
            <value locale="it-IT">Sab</value>	
        </resource>
        <resource id="41" type="string" name="TXT_SUN">		
            <value locale="en-GB">Sun</value>	
            <value locale="es-ES">Dom</value>	
            <value locale="de-DE">Son</value>	
            <value locale="fr-FR">Dim</value>	
            <value locale="it-IT">Dom</value>	
        </resource>
        <resource id="43" type="string" name="TXT_MENU_CAL">		
            <value locale="en-GB">Calendar</value>	
            <value locale="es-ES">Calendario</value>	
            <value locale="de-DE">Kalender</value>	
            <value locale="fr-FR">Calendrier</value>	
            <value locale="it-IT">Calendario</value>	
        </resource>
       <resource id="45" type="string" name="TXT_MENU_GRAPH">		
            <value locale="en-GB">Graph</value>	
            <value locale="es-ES">gráfico</value>	
            <value locale="de-DE">Graphik</value>	
            <value locale="fr-FR">Graphie</value>	
            <value locale="it-IT">Graphico</value>	
        </resource>
        <resource id="46" type="string" name="TXT_MENU_INFO">		
            <value locale="en-GB">Info</value>	
            <value locale="es-ES">Info</value>	
            <value locale="de-DE">Info</value>	
            <value locale="fr-FR">Infos</value>	
            <value locale="it-IT">Info</value>	
        </resource>
        <resource id="47" type="string" name="TXT_MENU_HELP">		
            <value locale="en-GB">Help</value>	
            <value locale="es-ES">ayudar</value>	
            <value locale="de-DE">helfen</value>	
            <value locale="fr-FR">aide</value>	
            <value locale="it-IT">aiuto</value>	
        </resource>
        <resource id="48" type="string" name="TXT_LABEL_HOME">		
            <value locale="en-GB">Home</value>	
            <value locale="es-ES">Inicio</value>	
            <value locale="de-DE">Startseit</value>	
            <value locale="fr-FR">Acceuille</value>	
            <value locale="it-IT">Home</value>	
        </resource>
        <resource id="49" type="string" name="TXT_SETTINGS_LANGUAGE_TITLE">		
            <value locale="en-GB">Language</value>	
            <value locale="es-ES">Idioma</value>	
            <value locale="de-DE">Sprache</value>	
            <value locale="fr-FR">Langue</value>	
            <value locale="it-IT">Lingua</value>	
        </resource>
        <resource id="50" type="string" name="TXT_SETTINGS_UNITS_TITLE">		
            <value locale="en-GB">Units</value>	
            <value locale="es-ES">Unidad</value>	
            <value locale="de-DE">Einheit</value>	
            <value locale="fr-FR">Unité</value>	
            <value locale="it-IT">unità</value>	
        </resource>
        <resource id="51" type="string" name="TXT_SETTINGS_PINCODE_TITLE">		
            <value locale="en-GB">Pin Code</value>	
            <value locale="es-ES">código PIN</value>	
            <value locale="de-DE">Pin-Code</value>	
            <value locale="fr-FR">Code Pin</value>	
            <value locale="it-IT">codice pin</value>	
        </resource>
        <resource id="52" type="string" name="TXT_SETTINGS_TARGET_TITLE">		
            <value locale="en-GB">Target Level</value>	
            <value locale="es-ES">Nivel objetivo</value>	
            <value locale="de-DE">Zielniveau</value>	
            <value locale="fr-FR">Niveau cible</value>	
            <value locale="it-IT">Livello di destinazione</value>	
        </resource>
        <resource id="53" type="string" name="TXT_SETTINGS_LANGUAGE_DESC">		
            <value locale="en-GB">Select your preferred language.</value>	
            <value locale="es-ES">Seleccione su idioma preferido.</value>
            <value locale="de-DE">Wählen Sie Ihre bevorzugte Sprache.</value>	
            <value locale="fr-FR">Choisissez votre langue préférée.</value>	
            <value locale="it-IT">Seleziona la tua lingua preferita.</value>	
        </resource>
        <resource id="54" type="string" name="TXT_SETTINGS_UNITS_DESC">		
            <value locale="en-GB">Select your blood sugar level unit for entering values.</value>	
            <value locale="es-ES">Seleccione su unidad de nivel de azúcar en la sangre para introducir valores.</value>	
            <value locale="de-DE">Wählen Sie Ihren Blutzuckerspiegel Gerät zur Eingabe von Werten.</value>	
            <value locale="fr-FR">Sélectionnez votre unité de niveau de sucre dans le sang pour entrer des valeurs.</value>	
            <value locale="it-IT">Selezionare l'unità di livello di zucchero nel sangue per l'immissione di valori.</value>	
        </resource>
        <resource id="55" type="string" name="TXT_SETTINGS_PINCODE_DESC">		
            <value locale="en-GB">If you select a PIN you will be prompted to enter it back on start up. Set it back to 0000 to deactivate authentication.</value>	
            <value locale="es-ES">Si selecciona un PIN se le pedirá que introduzca de nuevo el arranque. Ajuste de nuevo en 0000 para desactivar la autenticación.</value>	
            <value locale="de-DE">Wenn Sie eine PIN wählen, werden Sie aufgefordert, es zu betreten wieder starten werden. Setzen Sie ihn zurück auf 0000, um die Authentifizierung zu deaktivieren.</value>	
            <value locale="fr-FR">Si vous sélectionnez un code PIN, vous serez invité à entrer de nouveau au démarrage. Réglez-le à 0000 pour désactiver l'authentification.</value>	
            <value locale="it-IT">Se si seleziona un codice PIN ti verrà richiesto di inserire di nuovo in fase di start up. Impostare di nuovo a 0000 per disattivare l'autenticazione.</value>	
        </resource>
        <resource id="56" type="string" name="TXT_SETTINGS_TARGET_DESC">		
            <value locale="en-GB">Set a personal target level you want to acheive to measure your inputs against.</value>	
            <value locale="es-ES">Set a personal target level you want to acheive to measure your inputs against.</value>	
            <value locale="de-DE">Stellen Sie eine persönliche Zielniveau Sie acheive Ihre Eingaben gegen messen.</value>	
            <value locale="fr-FR">Définir un niveau cible personnels que vous voulez atteindre pour mesurer vos entrées contre.</value>	
            <value locale="it-IT">Impostare un livello obiettivo personale che si desidera acheive per misurare gli ingressi contro.</value>	
        </resource>
        <resource id="57" type="string" name="TXT_DIALOG_EXIT_TITLE">		
            <value locale="en-GB">Exit SweetTracker</value>	
            <value locale="es-ES">Dejar SweetTracker</value>	
            <value locale="de-DE">Verlassen SweetTracker</value>	
            <value locale="fr-FR">Quitter SweetTracker</value>	
            <value locale="it-IT">Lasciare SweetTracker</value>	
        </resource>
        <resource id="58" type="string" name="TXT_DIALOG_EXIT_DESC">		
            <value locale="en-GB">Would you like to exit SweetTracker</value>	
            <value locale="es-ES">Quieres salir?</value>	
            <value locale="de-DE">Möchten Sie SweetTracker beenden?</value>	
            <value locale="fr-FR">Voulez-vous quitter SweetTracker?</value>	
            <value locale="it-IT">Volete uscire?</value>	
        </resource>unauthorised
        <resource id="59" type="string" name="TXT_DIALOG_TITLE_UNAUTHORISED">		
            <value locale="en-GB">Unauthorised</value>	
            <value locale="es-ES">no autorizado</value>	
            <value locale="de-DE">Eigenmächtige</value>	
            <value locale="fr-FR">non autorisé</value>	
            <value locale="it-IT">non autorizzato</value>	
        </resource>
        <resource id="60" type="string" name="TXT_DIALOG_DESC_UNAUTHORISED">		
            <value locale="en-GB">Sorry, this feature is only available in the paid version.</value>	
            <value locale="es-ES">Lo sentimos, esta función sólo está disponible en la versión de pago.</value>	
            <value locale="de-DE">Leider ist diese Funktion nur in der kostenpflichtigen Version.</value>	
            <value locale="fr-FR">Désolé, cette option n'est disponible que dans la version payante.</value>	
            <value locale="it-IT">Spiacenti, questa funzione è disponibile solo nella versione a pagamento.</value>	
        </resource>
        <resource id="61" type="string" name="TXT_DIALOG_PIN_MSG">		
            <value locale="en-GB">Enter a memorable PIN.</value>	
            <value locale="es-ES">Introduzca un PIN memorable.</value>	
            <value locale="de-DE">Geben Sie einen unvergesslichen PIN.</value>	
            <value locale="fr-FR">Entrez un code PIN mémorable.</value>	
            <value locale="it-IT">Inserire un PIN memorabile.</value>	
        </resource>
        <resource id="62" type="string" name="TXT_DIALOG_PIN_TITLE">		
            <value locale="en-GB">Authentication</value>	
            <value locale="es-ES">Autenticación</value>	
            <value locale="de-DE">Beglaubigung</value>	
            <value locale="fr-FR">Authentification</value>	
            <value locale="it-IT">Autenticazione</value>	
        </resource>
        <resource id="63" type="string" name="TXT_MAPKEY_TODAY">		
            <value locale="en-GB">Today</value>	
            <value locale="es-ES">Hoy</value>	
            <value locale="de-DE">Heute</value>	
            <value locale="fr-FR">Aujourd'hui</value>	
            <value locale="it-IT">Oggi</value>	
        </resource>
        <resource id="64" type="string" name="TXT_MAPKEY_CRITICAL">		
            <value locale="en-GB">Critical</value>	
            <value locale="es-ES">Crítico</value>	
            <value locale="de-DE">Kritisch</value>	
            <value locale="fr-FR">Critique</value>	
            <value locale="it-IT">Critico</value>	
        </resource>
        <resource id="65" type="string" name="TXT_MAPKEY_NORMAL">		
            <value locale="en-GB">Normal</value>	
            <value locale="es-ES">Normal</value>	
            <value locale="de-DE">Normale</value>	
            <value locale="fr-FR">Normale</value>	
            <value locale="it-IT">Normale</value>	
        </resource>
        <resource id="66" type="string" name="TXT_MAPKEY_HIGH">		
            <value locale="en-GB">High</value>	
            <value locale="es-ES">Elevado</value>	
            <value locale="de-DE">Hoch</value>	
            <value locale="fr-FR">Elevé</value>	
            <value locale="it-IT">Alto</value>	
        </resource>
        <resource id="67" type="string" name="TXT_MENU_ENTRY">		
            <value locale="en-GB">Entry</value>	
            <value locale="es-ES">Apunte</value>	
            <value locale="de-DE">Vermerk</value>	
            <value locale="fr-FR">Entrée</value>	
            <value locale="it-IT">Annotazione</value>	
        </resource>
        <resource id="68" type="string" name="TXT_LEVEL_LESS_2_HOURS">		
            <value locale="en-GB">&lt; 2 hrs after meal</value>	
            <value locale="es-ES">&lt; 2 horas después de la comida</value>	
            <value locale="de-DE">&lt; 2 Stunden nach der Mahlzeit</value>	
            <value locale="fr-FR">&lt; 2 heures après le repas</value>	
            <value locale="it-IT">&lt; 2 ore dopo il pasto</value>	
        </resource>
        <resource id="69" type="string" name="TXT_LEVEL_BEFORE_MEAL">		
            <value locale="en-GB">Before meal</value>	
            <value locale="es-ES">Antes de la comida</value>	
            <value locale="de-DE">Vor dem Essen</value>	
            <value locale="fr-FR">Avant repas</value>	
            <value locale="it-IT">Prima del pasto</value>	
        </resource>
        <resource id="71" type="string" name="TXT_TAP_TO_EDIT">		
            <value locale="en-GB">Tap item to edit.</value>	
            <value locale="es-ES">Toque elemento que desea editar.</value>	
            <value locale="de-DE">Tippen Sie Artikel zu bearbeiten.</value>	
            <value locale="fr-FR">Tapez l'élément pour modifier.</value>	
            <value locale="it-IT">Toccare la voce da modificare.</value>	
        </resource>
        <resource id="72" type="string" name="TXT_SWIPE_TO_EDIT">		
            <value locale="en-GB">Swipe letf-right to change.</value>	
            <value locale="es-ES">Pase a la izquierda-derecha para cambiar.</value>	
            <value locale="de-DE">Swipe links-rechts zu ändern.</value>	
            <value locale="fr-FR">Faites glisser de gauche à droite pour changer.</value>	
            <value locale="it-IT">Swipe sinistra-destra per cambiare.</value>	
        </resource>
        <resource id="73" type="string" name="TXT_TAP_TO_ADD_NOTE">		
            <value locale="en-GB">Enter an additional note.</value>	
            <value locale="es-ES">Escriba una nota adicional.</value>	
            <value locale="de-DE">Geben Sie einen weiteren Hinweis.</value>	
            <value locale="fr-FR">Entrez une note supplémentaire.</value>	
            <value locale="it-IT">Inserisci una nota aggiuntiva.</value>	
        </resource>
        <resource id="74" type="string" name="TXT_SETTINGS_DIABETES_TYPE_TITLE">		
            <value locale="en-GB">Diabetes Type</value>	
            <value locale="es-ES">Diabetes tipo</value>	
            <value locale="de-DE">Diabetes Typ</value>	
            <value locale="fr-FR">Type de diabète</value>	
            <value locale="it-IT">Diabete di tipo</value>	
        </resource>
        <resource id="75" type="string" name="TXT_SETTINGS_DIABETES_TYPE_DESC">		
            <value locale="en-GB">Select one column to indicate if you are diabetic or not. The first range in each column is the normal 'Before meals' values. The range below is the 'After meals' values.</value>	
            <value locale="es-ES">Seleccione una columna para indicar si usted es diabético o no. El primer rango de cada columna es la normal "antes de las comidas" valores. El intervalo menor es el "después de las comidas" valores.</value>	
            <value locale="de-DE">Wählen Sie eine Spalte, um anzuzeigen, wenn Sie Diabetiker sind oder nicht. Der erste Bereich in jeder Spalte ist die normale "Vor dem Essen" Werte. Der Bereich unterhalb der "Nach dem Essen" Werte.</value>	
            <value locale="fr-FR">Sélectionnez une colonne pour indiquer si vous êtes diabétique ou non. La première gamme dans chaque colonne est la normale 'avant les repas de ses valeurs. La gamme ci-dessous est le 'après les repas de ses valeurs.</value>	
            <value locale="it-IT">Selezionare una colonna per indicare se si è diabetici o no. La prima gamma di ogni colonna è la normale 'prima dei pasti "valori. Il campo di sotto è il 'dopo i pasti "valori.</value>	
        </resource>
        <resource id="76" type="string" name="TXT_SETTINGS_DIABETES_TYPE_NONE">		
            <value locale="en-GB">None</value>	
            <value locale="es-ES">Nada</value>	
            <value locale="de-DE">Keine</value>	
            <value locale="fr-FR">Aucun</value>	
            <value locale="it-IT">Nessuno</value>	
        </resource>
        <resource id="77" type="string" name="TXT_SETTINGS_DIABETES_TYPE_ONE">		
            <value locale="en-GB">Type 1</value>	
            <value locale="es-ES">Tipo 1 1</value>	
            <value locale="de-DE">Typ 1</value>	
            <value locale="fr-FR">Type 1</value>	
            <value locale="it-IT">Tipo 1 1</value>	
        </resource>
        <resource id="78" type="string" name="TXT_SETTINGS_DIABETES_TYPE_TWO">		
            <value locale="en-GB">Type 2</value>	
            <value locale="es-ES">Tipo 2</value>	
            <value locale="de-DE">Typ 2</value>	
            <value locale="fr-FR">Type 2</value>	
            <value locale="it-IT">Tipo 2</value>	
        </resource>
        <resource id="79" type="string" name="TXT_DIALOG_TARGET_LEVEL_MSG">		
            <value locale="en-GB">Enter your target sugar level.</value>	
            <value locale="es-ES">Ingrese su nivel de azúcar blanco.</value>	
            <value locale="de-DE">Geben Sie Ihre Ziel-Blutzuckerspiegel.</value>	
            <value locale="fr-FR">Entrez votre taux de sucre ciblé.</value>	
            <value locale="it-IT">Inserisci il tuo livello di zucchero di destinazione.</value>	
        </resource>
        <resource id="80" type="string" name="TXT_DIALOG_TARGET_LEVEL_TITLE">		
            <value locale="en-GB">Target level</value>	
            <value locale="es-ES">nivel deseado</value>	
            <value locale="de-DE">Zielniveau</value>	
            <value locale="fr-FR">Niveau cible</value>	
            <value locale="it-IT">livello target</value>	
        </resource>
        <resource id="81" type="string" name="TXT_DIALOG_GLUCOSE_LEVEL_MSG">		
            <value locale="en-GB">Enter your current sugar level.</value>	
            <value locale="es-ES">Ingrese su nivel de azúcar en la actual.</value>	
            <value locale="de-DE">Geben Sie Ihre aktuellen Blutzuckerspiegel.</value>	
            <value locale="fr-FR">Entrez votre niveau actuel du sucre.</value>	
            <value locale="it-IT">Inserisci il tuo livello di zucchero nel corrente.</value>	
        </resource>
        <resource id="82" type="string" name="TXT_DIALOG_GLUCOSE_LEVEL_TITLE">		
            <value locale="en-GB">Glucose level</value>	
            <value locale="es-ES">El nivel de glucosa</value>	
            <value locale="de-DE">Glucose-Ebene</value>	
            <value locale="fr-FR">Niveau de glucose</value>	
            <value locale="it-IT">livello di glucosio</value>	
        </resource>
        <resource id="83" type="string" name="TXT_DIALOG_ENTRY_SAVED_TITLE">		
            <value locale="en-GB">Entry Saved</value>	
            <value locale="es-ES">Entrada Guardado</value>	
            <value locale="de-DE">Eintrag gespeichert</value>	
            <value locale="fr-FR">Entrée enregistrée</value>	
            <value locale="it-IT">Voce memorizzata</value>	
        </resource>
        <resource id="84" type="string" name="TXT_DIALOG_ENTRY_SAVED_MSG">		
            <value locale="en-GB">Entry successfully saved to your calendar.</value>	
            <value locale="es-ES">Entrada guardado correctamente a tu calendario.</value>	
            <value locale="de-DE">Eintrag erfolgreich zu Ihrem Kalender gespeichert.</value>	
            <value locale="fr-FR">Entrée sauvegardé à votre calendrier avec succès .</value>	
            <value locale="it-IT">Entrata salvato con successo al tuo calendario.</value>	
        </resource>
        <resource id="85" type="string" name="TXT_APP_DESC">	
            <value locale="en-GB">is designed to help you efficiently record and monitor your blood sugar levels. After entering your values you can use the calendar or graphs for data visualisation. It also evaluates your level and assigns it a critical level colour code. Tracking your blood sugar is now easy and effective.</value>	
            <value locale="es-ES">está diseñado para ayudarle a grabar de manera eficiente y controlar sus niveles de azúcar en la sangre. Después de introducir los valores que puede utilizar el calendario o gráficas para la visualización de datos. También evalúa su nivel y le asigna un código de color de nivel crítico. El seguimiento de su azúcar en la sangre ahora es fácil y eficaz.</value>	
            <value locale="de-DE">wurde entwickelt, um Ihnen helfen, effizient aufzeichnen und überwachen Sie Ihre Blutzuckerwerte. Nach Eingabe Ihrer Werte können Sie den Kalender oder Grafiken zur Visualisierung der Daten. Es wertet auch Ihr Niveau und ordnet sie ein kritisches Niveau Farbcode. Tracking Ihr Blutzucker ist nun einfach und effektiv.</value>	
            <value locale="fr-FR">est conçu pour vous aider à enregistrer et de surveiller efficacement votre taux de sucre dans le sang. Après avoir entré vos valeurs, vous pouvez utiliser le calendrier ou graphiques pour la visualisation des données. Il évalue également votre niveau et lui attribue un code de couleur critique de niveau. Le suivi de votre glycémie est maintenant facile et efficace.</value>	
            <value locale="it-IT">è progettato per aiutare a registrare in modo efficiente e monitorare i livelli di zucchero nel sangue. Dopo aver inserito i vostri valori è possibile utilizzare il calendario o grafici per la visualizzazione dei dati. Si valuta anche il tuo livello e assegna un codice colore di livello critico. Monitoraggio di zucchero nel sangue è ora facile ed efficace.</value>						
        </resource>
        <resource id="87" type="string" name="TXT_ABOUT_VERSION">		
            <value locale="en-GB">Version</value>	
            <value locale="es-ES">Versión</value>	
            <value locale="de-DE">Version</value>	
            <value locale="fr-FR">Version</value>	
            <value locale="it-IT">Versione</value>	
        </resource>
        <resource id="88" type="string" name="TXT_ABOUT_DEVELOPER">		
            <value locale="en-GB">Developer</value>	
            <value locale="es-ES">Promotor</value>	
            <value locale="de-DE">Entwickler</value>	
            <value locale="fr-FR">Développeur</value>	
            <value locale="it-IT">Sviluppatore</value>	
        </resource>
        <resource id="89" type="string" name="TXT_COMMON_ABOUT">		
            <value locale="en-GB">About</value>	
            <value locale="es-ES">Sobre</value>	
            <value locale="de-DE">über</value>	
            <value locale="fr-FR">À propos</value>	
            <value locale="it-IT">À propos</value>	
        </resource>
        <resource id="90" type="string" name="TXT_MENU_ACCEPT">		
            <value locale="en-GB">Accept</value>	
            <value locale="es-ES">Aceptar</value>	
            <value locale="de-DE">Akzeptieren</value>	
            <value locale="fr-FR">Accepter</value>	
            <value locale="it-IT">Accettare</value>	
        </resource>
        <resource id="91" type="string" name="TXT_MENU_DECLINE">		
            <value locale="en-GB">Decline</value>	
            <value locale="es-ES">Descenso</value>	
            <value locale="de-DE">Ablehnen</value>	
            <value locale="fr-FR">Refuser</value>	
            <value locale="it-IT">Declino</value>	
        </resource>
        <resource id="92" type="string" name="TXT_TERMS">		
            <value locale="en-GB">Terms</value>	
            <value locale="es-ES">Condiciones</value>	
            <value locale="de-DE">Bedingungen</value>	
            <value locale="fr-FR">Conditions</value>	
            <value locale="it-IT">Condizioni</value>	
        </resource>
        <resource id="93" type="string" name="TXT_TERMS_HEADER_1">		
            <value locale="en-GB">Introduction</value>	
            <value locale="es-ES">Introducción</value>	
            <value locale="de-DE">Einführung</value>	
            <value locale="fr-FR">Introduction</value>	
            <value locale="it-IT">Introduzione</value>	
        </resource>
        <resource id="94" type="string" name="TXT_TERMS_HEADER_2">		
            <value locale="en-GB">Liability</value>	
            <value locale="es-ES">Responsabilidad</value>	
            <value locale="de-DE">Haftung</value>	
            <value locale="fr-FR">Responsabilité</value>	
            <value locale="it-IT">Responsabilità</value>	
        </resource>
        <resource id="95" type="string" name="TXT_TERMS_HEADER_3">		
            <value locale="en-GB">Limited warranties</value>	
            <value locale="es-ES">Garantías limitadas</value>	
            <value locale="de-DE">Eingeschränkte Garantien</value>	
            <value locale="fr-FR">Les garanties limitées</value>	
            <value locale="it-IT">Garanzie limitate</value>	
        </resource>
        <resource id="96" type="string" name="TXT_TERMS_HEADER_4">		
            <value locale="en-GB">Indemnity</value>	
            <value locale="es-ES">Indemnidad</value>	
            <value locale="de-DE">Entschädigung</value>	
            <value locale="fr-FR">Indemnité</value>	
            <value locale="it-IT">Indennità</value>	
        </resource>
        <resource id="97" type="string" name="TXT_TERMS_DESC_1">		
            <value locale="en-GB">These terms and conditions govern your use of the mobile application SweetTracker. By using this application, you accept these terms and conditions in full. If you disagree with these terms and conditions or any part of these terms and conditions, you must not use SweetTracker.</value>	
            <value locale="es-ES">Estos términos y condiciones rigen el uso de la SweetTracker. de aplicaciones móviles. Al utilizar esta aplicación, usted acepta estos términos y condiciones en su totalidad. Si no está de acuerdo con estos términos y condiciones o cualquier parte de estos términos y condiciones, usted no debe utilizar SweetTracker.</value>	
            <value locale="de-DE">Diese Bedingungen regeln die Nutzung der mobilen Anwendung SweetTracker. Durch die Nutzung dieser Anwendung, akzeptieren Sie diese Bedingungen in vollem Umfang. Wenn Sie mit diesen Bedingungen oder einem Teil dieser Bedingungen und Konditionen nicht einverstanden sind, dürfen Sie nicht verwenden SweetTracker.</value>	
            <value locale="fr-FR">Ces termes et conditions régissent votre utilisation de SweetTracker. application mobile. En utilisant cette application, vous acceptez ces termes et conditions dans leur intégralité. Si vous êtes en désaccord avec ces termes et conditions ou toute partie de ces termes et conditions, vous ne devez pas utiliser SweetTracker.</value>	
            <value locale="it-IT">Questi termini e condizioni regolano l'utilizzo del SweetTracker. applicazione mobile. Utilizzando questa applicazione, l'utente accetta i termini e le condizioni in pieno. Se siete d'accordo con questi termini e condizioni o una parte di questi termini e condizioni, non si deve usare SweetTracker.</value>	
        </resource>
        <resource id="98" type="string" name="TXT_TERMS_DESC_2">		
            <value locale="en-GB">We will not be liable to you in respect of any losses arising out of any event or events beyond our reasonable control. We will not be liable to you in case you are wrongly diagnosed due to lack of precision in the software logic. We will not be liable to you in respect of any loss or corruption of any data, database or software.</value>	
            <value locale="es-ES">No seremos responsables ante usted con respecto a cualquier pérdida que se derive de cualquier evento o eventos fuera de nuestro control. No seremos responsables ante usted con respecto a cualquier pérdida o corrupción de datos, base de datos o software.</value>	
            <value locale="de-DE">Wir sind nicht haftbar zu machen für Schäden, die aus einer oder mehreren Ereignissen außerhalb unserer Kontrolle liegen. Wir sind nicht haftbar zu machen in Bezug auf einen Verlust oder die Beschädigung von Daten, Datenbanken oder Software.</value>	
            <value locale="fr-FR">Nous ne serons pas responsables envers vous pour toute perte découlant d'un événement ou d'événements indépendants de notre contrôle raisonnable. Nous ne serons pas responsables envers vous pour toute perte ou corruption des données, des bases de données ou de logiciels.</value>	
            <value locale="it-IT">Noi non saremo responsabili nei Vostri confronti di eventuali perdite derivanti da qualsiasi evento o eventi al di fuori del nostro ragionevole controllo. Non saremo responsabili nei vostri confronti per qualsiasi perdita o corruzione di, database di dati o software.</value>	
        </resource>
        <resource id="99" type="string" name="TXT_TERMS_DESC_3">		
            <value locale="en-GB">We do not warrant the completeness or accuracy of the information produced by this application; nor do we commit to ensuring that the application remains logical and reliable. To the maximum extent permitted by applicable law we exclude all representations, warranties and conditions relating to the use of this application (including, without limitation, any warranties implied by law of satisfactory quality, fitness for purpose and/or the use of reasonable care and skill).</value>	
            <value locale="es-ES">Nosotros no garantizamos la integridad y exactitud de la información generada por este software, ni tampoco nos comprometemos a garantizar que el software sigue siendo lógico y confiable. En la medida máxima permitida por la ley, excluimos todas las representaciones, garantías y condiciones relacionadas con el uso de esta aplicación (incluyendo, sin limitación, cualquier garantía implícita por la ley de calidad satisfactoria, aptitud para el uso y / o la utilización de un cuidado razonable y habilidad).</value>	
            <value locale="de-DE">Wir übernehmen keine Gewähr für die Vollständigkeit oder Genauigkeit der Informationen, die von dieser Software erzeugt werden; und  übernehmen  keine Gewähr dafür, dass die Software logisch und zuverlässig bleibt. In größtmöglichem Umfang, durch anwendbares Recht  erlaubt, schliessen wir alle Darstellungen, Garantien und Bedingungen in Bezug auf die Nutzung dieser Anwendung (einschließlich, ohne Einschränkung, sämtliche gesetzliche Gewährleistungen von zufriedenstellender Qualität impliziert, Zweckmäßigkeit und / oder die sorgflätige and angemessene Anwendung) aus.</value>	
            <value locale="fr-FR">Nous ne garantissons pas l'exhaustivité ou l'exactitude de l'information produite par ce logiciel, ni ne nous engageons à assurer que le logiciel reste logique et fiable. Dans la mesure maximale permise par la loi applicable l'on exclut toutes les représentations, garanties et conditions relatives à l'utilisation de cette application (y compris, sans limitation, toute garantie implicite par la loi de qualité satisfaisante, aptitude à l'usage et / ou l'utilisation d'un soin raisonnable et compétences).</value>	
            <value locale="it-IT">Noi non garantiamo la completezza o accuratezza delle informazioni prodotte da questo software, né ci impegniamo a garantire che il software rimanga logica e affidabile. Nella misura massima consentita dalla legge applicabile escludiamo tutti, garanzie e condizioni riguardanti l'uso di questa applicazione (inclusi, senza limitazione, qualsiasi garanzia implicita per legge di qualità soddisfacente, idoneità allo scopo e / o l'uso di ragionevole cura e abilità).</value>	
        </resource>
        <resource id="100" type="string" name="TXT_TERMS_DESC_4">		
            <value locale="en-GB">You hereby indemnify us and undertake to keep us indemnified against any losses, damages, costs, liabilities and expenses (including without limitation legal expenses and any amounts paid by us to a third party in settlement of a claim or dispute on the advice of our legal advisers) incurred or suffered by us arising out of any breach by you of any provision of these terms and conditions[, or arising out of any claim that you have breached any provision of these terms and conditions].</value>	
            <value locale="es-ES">Por la presente, nos indemnizará y nos comprometemos a mantenernos indemnizados por cualquier pérdida, daños, costos, responsabilidades y gastos (incluyendo, sin limitación de los gastos jurídicos y los importes pagados por nosotros los que una tercera parte en la solución de una demanda o disputa en el consejo de nuestro ordenamiento jurídico asesores) incurridos o sufridos por nosotros que surja de cualquier incumplimiento por su parte de cualquier disposición de estos términos y condiciones [o como resultado de cualquier reclamo que usted ha violado cualquier disposición de estos términos y condiciones].</value>	
            <value locale="de-DE">Sie erklären sich hiermit verpflichtet, und verpflichten sich weiterhin, uns gegen jegliche Verluste, Schäden, Kosten, Haftungen und Ausgaben die entstanden sind (einschließlich und ohne Einschränkung der legalen Kosten und aller Beträge, die, nach Beratung unseres Anwalts, durch Dritte in Erfüllung einer Forderung oder eines Streits entstehen), die sich aus einer Verletzung dieser Bedingungen und Konditionen Ihrerseits ergeben [oder die sich aus Ansprüchen ergeben, dass Sie eine Bestimmung dieser Bedingungen und Konditionen verletzt haben].</value>	
            <value locale="fr-FR">Par la présente vous nous indemniser et nous tenir s'engagent à indemniser toutes les pertes, dommages, coûts, responsabilités et dépenses (y compris, sans limitation les frais juridiques et tous les montants payés par nous à un tiers en règlement d'une réclamation ou litige sur les conseils de notre système juridique conseillers) engagés ou subis par nous découlant de toute violation par vous de toute disposition de ces termes et conditions [, ou découlant de toute réclamation que vous avez violé une disposition de ces termes et conditions].</value>	
            <value locale="it-IT">Con la presente ci risarcire e si impegnano a tenerci indenne da ogni perdita, danni, costi, oneri e spese (incluse senza limitazione le spese legali e gli importi pagati da noi a terzi in liquidazione di un sinistro o di controversia su consiglio dei nostri legali consulenti) sostenute o subite da noi derivanti da qualsiasi violazione da parte di qualsiasi disposizione di questi termini e condizioni [, o derivanti da qualsiasi pretesa che lei ha violato qualsiasi clausola di questi termini e condizioni].</value>	
        </resource>
        <resource id="101" type="string" name="TXT_DIALOG_TITLE_UNSUCCESSFUL">		
            <value locale="en-GB">Unsuccessful</value>	
            <value locale="es-ES">fracasado</value>	
            <value locale="de-DE">erfolglos</value>	
            <value locale="fr-FR">Échec</value>	
            <value locale="it-IT">fallito</value>	
        </resource>
        <resource id="102" type="string" name="TXT_DIALOG_TEXT_INVALID_INPUT">		
            <value locale="en-GB">Please try again with a valid input.</value>	
            <value locale="es-ES">Por favor, inténtelo de nuevo con una entrada válida.</value>	
            <value locale="de-DE">Bitte versuchen Sie es erneut mit einer gültigen Eingabe.</value>	
            <value locale="fr-FR">Veuillez essayer de nouveau avec une entrée valide.</value>	
            <value locale="it-IT">Riprova con un ingresso valido.</value>	
        </resource>
        <resource id="103" type="string" name="TXT_MENU_SETTINGS">		
            <value locale="en-GB">Settings</value>	
            <value locale="es-ES">Ajustes</value>	
            <value locale="de-DE">Einstellungen</value>	
            <value locale="fr-FR">Paramètres</value>	
            <value locale="it-IT">Impostazioni</value>	
        </resource>
        <resource id="104" type="string" name="TXT_SETTINGS_SAVED">		
            <value locale="en-GB">Your settings have been updated.</value>	
            <value locale="es-ES">Su configuración ha sido actualizada.</value>	
            <value locale="de-DE">Ihre Einstellungen wurden aktualisiert.</value>	
            <value locale="fr-FR">Vos paramètres ont été mis à jour.</value>	
            <value locale="it-IT">Le impostazioni sono state aggiornate.</value>	
        </resource>
        <resource id="105" type="string" name="TXT_DIALOG_TITLE_SUCCESSFUL">		
            <value locale="en-GB">Successful</value>	
            <value locale="es-ES">Exitosa.</value>	
            <value locale="de-DE">Erfolgreich.</value>	
            <value locale="fr-FR">Succès.</value>	
            <value locale="it-IT">Successo.</value>	
        </resource>
        <resource id="106" type="string" name="TXT_DIALOG_PIN_MSG_CONFIRM">		
            <value locale="en-GB">Confirm your memorable PIN.</value>	
            <value locale="es-ES">Confirme su PIN memorable.</value>	
            <value locale="de-DE">Bestätigen Sie Ihre PIN unvergesslich.</value>	
            <value locale="fr-FR">Confirmez votre code PIN mémorable.</value>	
            <value locale="it-IT">Confermare il PIN memorabile.</value>	
        </resource>
        <resource id="107" type="string" name="TXT_LOCK_ON">		
            <value locale="en-GB">PIN locked mode</value>	
            <value locale="es-ES">PIN modo de bloqueo</value>	
            <value locale="de-DE">PIN gesperrt Modus</value>	
            <value locale="fr-FR">Mode PIN verrouillé</value>	
            <value locale="it-IT">PIN modalità bloccata</value>	
        </resource>
        <resource id="108" type="string" name="TXT_LOCK_OFF">		
            <value locale="en-GB">No PIN specified</value>	
            <value locale="es-ES">Sin PIN especificado</value>	
            <value locale="de-DE">Keine PIN angegeben</value>	
            <value locale="fr-FR">Aucun PIN spécifié</value>	
            <value locale="it-IT">No PIN specificato</value>	
        </resource>
        <resource id="109" type="string" name="TXT_THEME_TITLE">		
            <value locale="en-GB">Theme</value>	
            <value locale="es-ES">tema</value>	
            <value locale="de-DE">Theme</value>	
            <value locale="fr-FR">thème</value>	
            <value locale="it-IT">argomento</value>	
        </resource>
        <resource id="110" type="string" name="TXT_THEME_DESC">		
            <value locale="en-GB">Select your favourite theme for the application.</value>	
            <value locale="es-ES">Elige tu tema favorito de la aplicación.</value>	
            <value locale="de-DE">Wählen Sie Ihre Lieblings-Thema für die Anwendung.</value>	
            <value locale="fr-FR">Choisissez votre thème favori de l'application.</value>	
            <value locale="it-IT">Seleziona il tema che preferisci per l'applicazione.</value>	
        </resource>
        <resource id="111" type="string" name="TXT_DAYS">		
            <value locale="en-GB">Days</value>	
            <value locale="es-ES">días</value>	
            <value locale="de-DE">Tage</value>	
            <value locale="fr-FR">jours</value>	
            <value locale="it-IT">giorni</value>	
        </resource>
        <resource id="112" type="string" name="TXT_DELETE">		
            <value locale="en-GB">Delete</value>	
            <value locale="es-ES">borrar</value>	
            <value locale="de-DE">löschen</value>	
            <value locale="fr-FR">supprimer</value>	
            <value locale="it-IT">Cancella</value>	
        </resource>
        <resource id="113" type="string" name="TXT_ENTRY_DELETED">		
            <value locale="en-GB">Entry was deleted.</value>	
            <value locale="es-ES">La entrada ha sido eliminada.</value>	
            <value locale="de-DE">Der Eintrag wurde gelöscht.</value>	
            <value locale="fr-FR">L'entrée a été supprimé.</value>	
            <value locale="it-IT">Voce è stata cancellata.</value>	
        </resource>
       <resource id="114" type="string" name="TXT_ENTRY_HELP_TITLE_0">		
            <value locale="en-GB">Setting diabetes type</value>	
            <value locale="es-ES">Ajuste del tipo de diabetes</value>	
            <value locale="de-DE">Einstellen Diabetes Typ</value>	
            <value locale="fr-FR">Type de diabete</value>	
            <value locale="it-IT">Impostazione del tipo di diabete</value>	
        </resource>
        <resource id="115" type="string" name="TXT_ENTRY_HELP_TITLE_1">		
            <value locale="en-GB">Adding a calendar entry</value>	
            <value locale="es-ES">Adición de una entrada de agenda</value>	
            <value locale="de-DE">Hinzufügen einen Kalendereintrag</value>	
            <value locale="fr-FR">Ajout d'une entrée de calendrier</value>	
            <value locale="it-IT">Aggiunta di una voce del calendario</value>	
        </resource>
        <resource id="116" type="string" name="TXT_ENTRY_HELP_TITLE_2">		
            <value locale="en-GB">Glucose level charts</value>	
            <value locale="es-ES">Gráficos de nivel de glucosa</value>	
            <value locale="de-DE">Glucose Ebene Charts</value>	
            <value locale="fr-FR">Cartes de niveau de glucose</value>	
            <value locale="it-IT">Carte di livello di glucosio</value>	
        </resource>
        <resource id="117" type="string" name="TXT_ENTRY_HELP_TITLE_3">		
            <value locale="en-GB">Colour coding</value>	
            <value locale="es-ES">código de colores</value>	
            <value locale="de-DE">Farbcodierung</value>	
            <value locale="fr-FR">Code couleur</value>	
            <value locale="it-IT">codificazione del colore</value>	
        </resource>
        <resource id="118" type="string" name="TXT_ENTRY_HELP_TITLE_4">		
            <value locale="en-GB">Change theme</value>	
            <value locale="es-ES">Cambiar el tema</value>	
            <value locale="de-DE">ändern Thema</value>	
            <value locale="fr-FR">changer le thème</value>	
            <value locale="it-IT">cambiare tema</value>	
        </resource>
        <resource id="119" type="string" name="TXT_ENTRY_HELP_TITLE_5">		
            <value locale="en-GB">Setting a PIN lock</value>	
            <value locale="es-ES">El establecimiento de un bloqueo de PIN</value>	
            <value locale="de-DE">Festlegen einer PIN-Sperre</value>	
            <value locale="fr-FR">Définir un verrouillage par code PIN</value>	
            <value locale="it-IT">Impostazione di un blocco PIN</value>	
        </resource>
        <resource id="120" type="string" name="TXT_ENTRY_HELP_DESC_0">		
            <value locale="en-GB">Before you start entering values please update your diabetes type appropriately. In the settings screen you can specify if you are a non-diabetic, diabetes type 1 or diabetes type 2. You will notice that before meal and after meal values vary depending on your selected type. Those values are later used to determine your colour code and if you are exceeding expected levels.</value>	
            <value locale="es-ES">Antes de comenzar a introducir los valores por favor, actualice su diabetes tipo adecuadamente. En la pantalla de configuración se puede especificar si es un no diabético, diabetes tipo 1 o diabetes tipo 2. Usted se dará cuenta de que antes de comer y después de las comidas valores varían dependiendo del tipo seleccionado. Estos valores se utilizan después para determinar el código de color y si superas los niveles esperados.</value>	
            <value locale="de-DE">Bevor Sie mit der Eingabe beginnen Werte aktualisieren Sie bitte Ihre Diabetes Typ entsprechend. In den Einstellungen können Sie angeben können, wenn Sie eine nicht-diabetischen, Diabetes Typ 1 oder Typ 2 Diabetes sind. Sie werden feststellen, dass vor dem Essen und nach dem Essen Werte abhängig von Ihrem gewählten Art variieren. Diese Werte werden später verwendet, um Deine Farbe bestimmen und wenn Sie mehr als erwartete Niveau.</value>	
            <value locale="fr-FR">Avant de commencer la saisie des valeurs Veuillez mettre à jour votre diabète de type appropriée. Dans l'écran des paramètres, vous pouvez spécifier si vous êtes un non-diabétique, le diabète de type 1 ou diabète de type 2. Vous remarquerez que avant le repas et après les valeurs de repas varient en fonction du type sélectionné. Ces valeurs sont ensuite utilisées pour déterminer votre code couleur et si vous dépassez les niveaux attendus.</value>	
            <value locale="it-IT">Prima di iniziare a immettere i valori si prega di aggiornare il vostro diabete di tipo appropriato. Nella schermata delle impostazioni è possibile specificare se si è un non-diabetico, diabete di tipo 1 o diabete di tipo 2. Si noterà che prima del pasto e dopo pasto valori variano a seconda del tipo selezionato. Questi valori vengono poi utilizzati per determinare il codice colore e se si superano i livelli attesi.</value>	
        </resource>
        <resource id="121" type="string" name="TXT_ENTRY_HELP_DESC_1">		
            <value locale="en-GB">To make an entry in your calendar select the  calendar menu from the menu screen. The calendar opens in a monthly view with the current day shown as blue. All previous entries for the month are also shown. Tapping on a calendar's day takes you to the entry screen where you can set the glucose value and any additional note.</value>	
            <value locale="es-ES">Para crear una entrada en el calendario, seleccione el menú de calendario desde la pantalla de menú. El calendario se abre en una vista mensual por el día actual se muestra en color azul. También se muestran todos los registros anteriores para el mes. Al tocar en un día de calendario le lleva a la pantalla de entrada donde se puede establecer el valor de glucosa y cualquier nota adicional.</value>	
            <value locale="de-DE">Um einen Eintrag in Ihrem Kalender wählen Sie das Menü Kalender aus dem Menü-Bildschirm. Der Kalender wird in einer Monatsübersicht mit den aktuellen Tag als blau dargestellt. Alle bisherigen Einträge für den Monat werden auch gezeigt. Tippen auf einem Kalender Tag führt Sie zur Eingabemaske, wo Sie die Glukose-Wert und keine zusätzlichen beachten können.</value>	
            <value locale="fr-FR">Pour faire une entrée dans votre calendrier sélectionner le menu du calendrier à partir de l'écran de menu. Le calendrier s'ouvre dans une vue mensuelle, le jour courant montré que le bleu. Toutes les entrées précédentes pour le mois sont également représentées. En tapant sur la journée d'un calendrier vous emmène à l'écran de saisie où vous pouvez définir la valeur de la glycémie et une note complémentaire.</value>	
            <value locale="it-IT">Per creare una voce nel calendario selezionare il menu calendario dalla schermata del menu. Il calendario si apre in una vista mensile con il giorno corrente evidenziato in blu. Sono indicate anche tutte le voci precedenti per il mese. Toccando il giorno di un calendario vi porta alla schermata di inserimento in cui è possibile impostare il valore di glucosio e di eventuali note aggiuntive>.</value>	
        </resource>
        <resource id="122" type="string" name="TXT_ENTRY_HELP_DESC_2">		
            <value locale="en-GB">After you have made any entry you can select the charts menu from the menu screen to visualise your monthly entries on a bar chart. The chart for a month contains all entries made and your specified target is shown as a grey horizontal line. This is so that you can measure your levels against it.</value>	
            <value locale="es-ES">Después de haber hecho cualquier entrada se puede seleccionar el menú de gráficos de la pantalla del menú para visualizar sus entradas mensuales en un gráfico de barras. La carta hace un mes contiene todas las entradas, y cuando el destino especificado se muestra como una línea horizontal gris. Esto es para que usted pueda medir sus niveles en contra de ella.</value>	
            <value locale="de-DE">Nachdem Sie einen Eintrag gemacht haben, können Sie das Diagramm-Menü aus dem Menü-Bildschirm, um Ihre monatlichen Einträge auf einem Balkendiagramm visualisieren. Die Grafik für einen Monat enthält alle Einträge gemacht und Ihr Ziel angegeben wird als graue horizontale Linie dargestellt. Dies ist so, dass Sie Ihre Ebenen gegen sie zu messen.</value>	
            <value locale="fr-FR">Après avoir fait une entrée, vous pouvez sélectionner le menu graphiques de l'écran de menu pour visualiser vos entrées mensuelles sur un graphique à barres. Le tableau pendant un mois contient toutes les inscriptions faites et votre cible spécifiée est représenté par une ligne horizontale grise. C'est ainsi que vous pouviez mesurer votre niveau contre elle.</value>	
            <value locale="it-IT">Dopo aver effettuato una voce è possibile selezionare il menu grafici dalla schermata del menu per visualizzare le voci mensili su un grafico a barre. La tabella per un mese contiene tutte le voci fatte e il vostro target specificato viene visualizzato come una linea orizzontale grigia. Questo è così che si può misurare i livelli contro di essa.</value>	
        </resource>
        <resource id="123" type="string" name="TXT_ENTRY_HELP_DESC_3">		
            <value locale="en-GB">3 distinct colour codes are used to denote your glucose level category. When an entered level is within the expected range it is green. If the level borders the higher upper limit of the range it is then set to high with an orange colour. A critical red colour is assigned when the value exceeds the diabetes type expected range. Those ranges are define in the settings screen when you specifi what type of diabetic you are. </value>	
            <value locale="es-ES">3 códigos de color diferentes se utilizan para denotar la categoría de su nivel de glucosa. Cuando un nivel introducido debe estar dentro del rango esperado es de color verde. Si el nivel limita con el límite superior más alta de la gama que se ajusta entonces a alta con un color naranja. Un color rojo crítico se asigna cuando el valor excede el rango esperado la diabetes tipo. Los rangos se definen en la pantalla de configuración cuando específicamente qué tipo de diabetes está.</value>	
            <value locale="de-DE">3 verschiedene Farbcodes werden verwendet, um Ihren Blutzuckerspiegel Kategorie bezeichnen. Wenn eine Eingabe innerhalb des erwarteten Bereichs ist es grün ist. Wenn der Pegel grenzt an die höheren oberen Grenze des Bereichs ist dann hoch, mit einer orange Farbe. Eine kritische rote Farbe zugewiesen wird, wenn der Wert den Diabetes Typ erwartet Bereich überschreitet. Diese Bereiche werden in den Einstellungen festlegen, wann Bildschirm Spezifikation, welche Art der diabetischen Sie sind.</value>	
            <value locale="fr-FR">3 codes de couleurs distincts sont utilisés pour désigner la catégorie de votre niveau de glucose. Quand un niveau est entré dans la fourchette attendue, il est vert. Si le niveau borde la limite supérieure supérieure de la fourchette, il est alors mis à haute avec une couleur orange. Une couleur rouge critique est affecté lorsque la valeur dépasse le type de la plage attendue de diabète. Ces gammes sont définissent dans l'écran des paramètres lorsque vous spécifiquement ce type de diabétique, vous êtes.</value>	
            <value locale="it-IT">3 codici di colore distinti sono usati per indicare il livello di glucosio categoria di livello. Quando un livello di entrata è compreso nell'intervallo previsto è verde. Se il livello delimita il limite superiore più alte della gamma viene quindi impostata alto con un colore arancione. Un colore rosso critica viene assegnato quando il valore supera il diabete di tipo range previsto. Tali intervalli sono definiscono nella schermata delle impostazioni quando si specifi che tipo di diabete si è.</value>	
        </resource>
        <resource id="124" type="string" name="TXT_ENTRY_HELP_DESC_4">		
            <value locale="en-GB">The application support 2 seperate themes namely blue and pink. You can set your theme in the settings screen by simply tapping on the appropriate icon. Note that this feature is only available in the full version of this application.</value>	
            <value locale="es-ES">El soporte de aplicaciones 2 temas separados a saber, azul y rosa. Puede configurar el tema de la pantalla de configuración con un simple toque en el icono correspondiente. Tenga en cuenta que esta característica sólo está disponible en la versión completa de esta aplicación.</value>	
            <value locale="de-DE">Die Anwendung unterstützt 2 getrennte Themen nämlich blau und rosa. Sie können Ihr Thema in den Einstellungen Bildschirm gesetzt einfach durch Antippen auf das entsprechende Symbol. Beachten Sie, dass diese Funktion nur in der Vollversion von dieser Anwendung zur Verfügung.</value>	
            <value locale="fr-FR">L'application a 2 thèmes distincts; le bleu et le rose. Vous pouvez configurer votre thème dans l'écran des paramètres en tapant simplement sur l'icône appropriée. Notez que cette fonctionnalité n'est disponible que dans la version complète de cette application.</value>	
            <value locale="it-IT">Il supporto di applicazione due temi separati ovvero blu e rosa. È possibile impostare il tema nella schermata impostazioni semplicemente toccando l'icona appropriata. Si noti che questa funzione è disponibile solo nella versione completa di questa applicazione.</value>	
        </resource>
        <resource id="125" type="string" name="TXT_ENTRY_HELP_DESC_5">		
            <value locale="en-GB">You can preserve the privacy of your entries by locking the application with a PIN code. Setting a PIN in the settings screen will ensure that you get prompted to re enter it everytime the application starts. To cancel just set the PIN to 0000. Note that this feature is only available in the full version of this application.</value>	
            <value locale="es-ES">Puede preservar la privacidad de sus entradas mediante el bloqueo de la aplicación con un código PIN. El establecimiento de un PIN en la pantalla de configuración se asegurará de que te le pedirá que vuelva a introducirla cada vez que se inicia la aplicación. Para cancelar acaba de establecer el PIN a 0000. Tenga en cuenta que esta característica sólo está disponible en la versión completa de esta aplicación.</value>	
            <value locale="de-DE">Sie können den Schutz Ihrer Einträge durch Verriegeln der Anwendung mit einem PIN-Code zu erhalten. Festlegen einer PIN in den Einstellungen angezeigt wird sichergestellt, dass Sie aufgefordert zu werden, wieder geben es jedes Mal die Anwendung startet. So brechen Sie einfach die PIN auf 0000. Beachten Sie, dass diese Funktion nur in der Vollversion von dieser Anwendung zur Verfügung.</value>	
            <value locale="fr-FR">Vous pouvez conserver la confidentialité de vos données en verrouillant l'application avec un code PIN. Définir un code PIN dans l'écran Paramètres veillera à ce que vous êtes de nouveau invité à entrer chaque fois que l'application démarre. Pour annuler veuillez remettre le code PIN à 0000. Notez que cette fonctionnalité n'est disponible que dans la version complète de cette application.</value>	
            <value locale="it-IT">È possibile preservare la privacy dei vostri voci bloccando l'applicazione con un codice PIN. Impostazione di un codice PIN nella schermata Impostazioni farà in modo che si ottiene viene richiesto di immetterla nuovamente ogni volta l'applicazione si avvia. Per cancellare basta impostare il PIN 0000. Si noti che questa funzione è disponibile solo nella versione completa di questa applicazione.</value>	
        </resource>
    </set>
</resources>

